datetime2/__init__.py
datetime2/common.py
datetime2/modern.py
datetime2/western.py
datetime2-0.9.2.dist-info/LICENSE.txt
datetime2-0.9.2.dist-info/METADATA
datetime2-0.9.2.dist-info/WHEEL
datetime2-0.9.2.dist-info/top_level.txt
datetime2-0.9.2.dist-info/RECORD
