Metadata-Version: 2.1
Name: datetime2
Version: 0.9.2
Summary: New date and time classes
Home-page: https://github.com/fricciardi/datetime2
Author: Francesco Ricciardi
Author-email: francescor2010@yahoo.it
License: BSD License
Project-URL: Documentation, https://datetime2.readthedocs.io/en/stable/
Project-URL: Issue Tracker, https://github.com/fricciardi/datetime2/issues
Project-URL: Source, https://github.com/fricciardi/datetime2
Keywords: date time datetime calendar
Platform: Platform independent
Classifier: Development Status :: 3 - Alpha
Classifier: License :: OSI Approved :: BSD License
Classifier: Operating System :: OS Independent
Classifier: Programming Language :: Python :: 3.8
Classifier: Programming Language :: Python :: 3.9
Classifier: Programming Language :: Python :: 3.10
Classifier: Topic :: Scientific/Engineering
Classifier: Topic :: Software Development :: Libraries :: Python Modules
License-File: LICENSE.txt
